setup.py
bin/tcx2rk
tcx2rk/__init__.py
tcx2rk/__main__.py
tcx2rk/_version.py
tcx2rk/conversion.py
tcx2rk/healthgraph.py
tcx2rk/tcx.py
tcx2rk.egg-info/PKG-INFO
tcx2rk.egg-info/SOURCES.txt
tcx2rk.egg-info/dependency_links.txt
tcx2rk.egg-info/requires.txt
tcx2rk.egg-info/top_level.txt