Metadata-Version: 1.0
Name: tcx2rk
Version: 0.1.2
Summary: Convert TCX files to the Runkeeper format
Home-page: https://github.com/brendanmaguire/tcx2rk
Author: Brendan Maguire
Author-email: maguire.brendan@gmail.com
License: Apache 2.0
Platform: UNKNOWN
